cdt/__init__.py
cdt/area_classification.py
cdt/cdt_feature.csv
cdt/cdt_feature_creator.py
cdt/cdt_util.py
cdt/clock.py
cdt/digit_classification.py
cdt/explanation_creator.py
cdt/hand.py
cdt/kmeans.model
cdt/rf.m
cdt/storke_segmentation.py
cdt/stroke_classification.py
cdt/svm_train_1_model.m
cdt/train1_model.m
cdt/ckpt_cdt/__init__.py
cdt/ckpt_cdt/cdt.ckpt-31300.data-00000-of-00001
cdt/ckpt_cdt/cdt.ckpt-31300.index
cdt/ckpt_cdt/cdt.ckpt-31300.meta
cdt/ckpt_cdt/checkpoint
cdt/ckpt_cdt/__pycache__/__init__.cpython-37.pyc
cdt_test-0.2.3.dist-info/METADATA
cdt_test-0.2.3.dist-info/WHEEL
cdt_test-0.2.3.dist-info/top_level.txt
cdt_test-0.2.3.dist-info/RECORD
